{
    "identification": {
        "id": "345789e6",
        "row": 5480611129,
        "number": {
            "default": "CZ3061",
            "alternative": null
        },
        "callsign": "CSN3061"
    },
    "status": {
        "live": true,
        "text": "Estimated- 14:52",
        "icon": "green",
        "estimated": null,
        "ambiguous": false,
        "generic": {
            "status": {
                "text": "estimated",
                "color": "green",
                "type": "arrival"
            },
            "eventTime": {
                "utc": 1710309120,
                "local": 1710341520
            }
        }
    },
    "level": "limited",
    "promote": false,
    "aircraft": {
        "model": {
            "code": "A20N",
            "text": "Airbus A320-251N"
        },
        "countryId": 46,
        "registration": "B-301H",
        "age": null,
        "msn": null,
        "images": {
            "thumbnails": [
                {
                    "src": "https://cdn.jetphotos.com/200/6/2339268_1708270485_tb.jpg?v=0",
                    "link": "https://www.jetphotos.com/photo/11251791",
                    "copyright": "Neil Patrick John Dariagan",
                    "source": "Jetphotos"
                },
                {
                    "src": "https://cdn.jetphotos.com/200/6/1007016_1705029423_tb.jpg?v=0",
                    "link": "https://www.jetphotos.com/photo/11206932",
                    "copyright": "Eric Wang",
                    "source": "Jetphotos"
                },
                {
                    "src": "https://cdn.jetphotos.com/200/5/1958711_1704735762_tb.jpg?v=0",
                    "link": "https://www.jetphotos.com/photo/11202762",
                    "copyright": "AMGEnthusiast63",
                    "source": "Jetphotos"
                },
                {
                    "src": "https://cdn.jetphotos.com/200/6/708421_1703417683_tb.jpg?v=0",
                    "link": "https://www.jetphotos.com/photo/11168198",
                    "copyright": "Grimoire",
                    "source": "Jetphotos"
                },
                {
                    "src": "https://cdn.jetphotos.com/200/5/678073_1693927242_tb.jpg?v=0",
                    "link": "https://www.jetphotos.com/photo/11082129",
                    "copyright": "w9r",
                    "source": "Jetphotos"
                }
            ],
            "medium": [
                {
                    "src": "https://cdn.jetphotos.com/400/6/2339268_1708270485.jpg?v=0",
                    "link": "https://www.jetphotos.com/photo/11251791",
                    "copyright": "Neil Patrick John Dariagan",
                    "source": "Jetphotos"
                },
                {
                    "src": "https://cdn.jetphotos.com/400/6/1007016_1705029423.jpg?v=0",
                    "link": "https://www.jetphotos.com/photo/11206932",
                    "copyright": "Eric Wang",
                    "source": "Jetphotos"
                },
                {
                    "src": "https://cdn.jetphotos.com/400/5/1958711_1704735762.jpg?v=0",
                    "link": "https://www.jetphotos.com/photo/11202762",
                    "copyright": "AMGEnthusiast63",
                    "source": "Jetphotos"
                },
                {
                    "src": "https://cdn.jetphotos.com/400/6/708421_1703417683.jpg?v=0",
                    "link": "https://www.jetphotos.com/photo/11168198",
                    "copyright": "Grimoire",
                    "source": "Jetphotos"
                },
                {
                    "src": "https://cdn.jetphotos.com/400/5/678073_1693927242.jpg?v=0",
                    "link": "https://www.jetphotos.com/photo/11082129",
                    "copyright": "w9r",
                    "source": "Jetphotos"
                }
            ],
            "large": [
                {
                    "src": "https://cdn.jetphotos.com/640cb/6/2339268_1708270485.jpg?v=0",
                    "link": "https://www.jetphotos.com/photo/11251791",
                    "copyright": "Neil Patrick John Dariagan",
                    "source": "Jetphotos"
                },
                {
                    "src": "https://cdn.jetphotos.com/640cb/6/1007016_1705029423.jpg?v=0",
                    "link": "https://www.jetphotos.com/photo/11206932",
                    "copyright": "Eric Wang",
                    "source": "Jetphotos"
                },
                {
                    "src": "https://cdn.jetphotos.com/640cb/5/1958711_1704735762.jpg?v=0",
                    "link": "https://www.jetphotos.com/photo/11202762",
                    "copyright": "AMGEnthusiast63",
                    "source": "Jetphotos"
                },
                {
                    "src": "https://cdn.jetphotos.com/640cb/6/708421_1703417683.jpg?v=0",
                    "link": "https://www.jetphotos.com/photo/11168198",
                    "copyright": "Grimoire",
                    "source": "Jetphotos"
                },
                {
                    "src": "https://cdn.jetphotos.com/640cb/5/678073_1693927242.jpg?v=0",
                    "link": "https://www.jetphotos.com/photo/11082129",
                    "copyright": "w9r",
                    "source": "Jetphotos"
                }
            ]
        },
        "hex": "7814b6"
    },
    "airline": {
        "name": "China Southern Airlines (PICC Livery)",
        "short": "China Southern Airlines",
        "code": {
            "iata": "CZ",
            "icao": "CSN"
        },
        "url": "china-southern-airlines-csn"
    },
    "owner": null,
    "airspace": null,
    "airport": {
        "origin": {
            "name": "Guangzhou Baiyun International Airport",
            "code": {
                "iata": "CAN",
                "icao": "ZGGG"
            },
            "position": {
                "latitude": 23.392429,
                "longitude": 113.298698,
                "altitude": 50,
                "country": {
                    "id": 46,
                    "name": "China",
                    "code": "CN",
                    "codeLong": "CHN"
                },
                "region": {
                    "city": "Guangzhou"
                }
            },
            "timezone": {
                "name": "Asia/Shanghai",
                "offset": 28800,
                "offsetHours": "8:00",
                "abbr": "CST",
                "abbrName": "China Standard Time",
                "isDst": false
            },
            "visible": true,
            "website": "http://www.gbiac.net/en/byhome",
            "info": {
                "terminal": "2",
                "baggage": null,
                "gate": "K,P"
            }
        },
        "destination": {
            "name": "Seoul Incheon International Airport",
            "code": {
                "iata": "ICN",
                "icao": "RKSI"
            },
            "position": {
                "latitude": 37.46907,
                "longitude": 126.4505,
                "altitude": 23,
                "country": {
                    "id": 207,
                    "name": "South Korea",
                    "code": "KR",
                    "codeLong": "KOR"
                },
                "region": {
                    "city": "Seoul"
                }
            },
            "timezone": {
                "name": "Asia/Seoul",
                "offset": 32400,
                "offsetHours": "9:00",
                "abbr": "KST",
                "abbrName": "Korea Standard Time",
                "isDst": false
            },
            "visible": true,
            "website": "http://www.airport.kr/eng/",
            "info": {
                "terminal": "1",
                "baggage": "13",
                "gate": "125"
            }
        },
        "real": null
    },
    "flightHistory": {
        "aircraft": [
            {
                "identification": {
                    "id": "34570931",
                    "number": {
                        "default": "CZ6282"
                    }
                },
                "airport": {
                    "origin": {
                        "name": "Xuzhou Guanyin Airport",
                        "code": {
                            "iata": "XUZ",
                            "icao": "ZSXZ"
                        },
                        "position": {
                            "latitude": 34.052925,
                            "longitude": 117.554077,
                            "altitude": 66,
                            "country": {
                                "id": null,
                                "name": "China",
                                "code": "CHN"
                            },
                            "region": {
                                "city": "Xuzhou"
                            }
                        },
                        "timezone": {
                            "name": "Asia/Shanghai",
                            "offset": 28800,
                            "offsetHours": "8:00",
                            "abbr": "CST",
                            "abbrName": "China Standard Time",
                            "isDst": false
                        },
                        "visible": true,
                        "website": null
                    },
                    "destination": {
                        "name": "Guangzhou Baiyun International Airport",
                        "code": {
                            "iata": "CAN",
                            "icao": "ZGGG"
                        },
                        "position": {
                            "latitude": 23.392429,
                            "longitude": 113.298698,
                            "altitude": 50,
                            "country": {
                                "id": 46,
                                "name": "China",
                                "code": "CN",
                                "codeLong": "CHN"
                            },
                            "region": {
                                "city": "Guangzhou"
                            }
                        },
                        "timezone": {
                            "name": "Asia/Shanghai",
                            "offset": 28800,
                            "offsetHours": "8:00",
                            "abbr": "CST",
                            "abbrName": "China Standard Time",
                            "isDst": false
                        },
                        "visible": true,
                        "website": "http://www.gbiac.net/en/byhome"
                    }
                },
                "time": {
                    "real": {
                        "departure": 1710284820
                    }
                }
            },
            {
                "identification": {
                    "id": "345570e1",
                    "number": {
                        "default": "CZ6281"
                    }
                },
                "airport": {
                    "origin": {
                        "name": "Guangzhou Baiyun International Airport",
                        "code": {
                            "iata": "CAN",
                            "icao": "ZGGG"
                        },
                        "position": {
                            "latitude": 23.392429,
                            "longitude": 113.298698,
                            "altitude": 50,
                            "country": {
                                "id": 46,
                                "name": "China",
                                "code": "CN",
                                "codeLong": "CHN"
                            },
                            "region": {
                                "city": "Guangzhou"
                            }
                        },
                        "timezone": {
                            "name": "Asia/Shanghai",
                            "offset": 28800,
                            "offsetHours": "8:00",
                            "abbr": "CST",
                            "abbrName": "China Standard Time",
                            "isDst": false
                        },
                        "visible": true,
                        "website": "http://www.gbiac.net/en/byhome"
                    },
                    "destination": {
                        "name": "Xuzhou Guanyin Airport",
                        "code": {
                            "iata": "XUZ",
                            "icao": "ZSXZ"
                        },
                        "position": {
                            "latitude": 34.052925,
                            "longitude": 117.554077,
                            "altitude": 66,
                            "country": {
                                "id": null,
                                "name": "China",
                                "code": "CHN"
                            },
                            "region": {
                                "city": "Xuzhou"
                            }
                        },
                        "timezone": {
                            "name": "Asia/Shanghai",
                            "offset": 28800,
                            "offsetHours": "8:00",
                            "abbr": "CST",
                            "abbrName": "China Standard Time",
                            "isDst": false
                        },
                        "visible": true,
                        "website": null
                    }
                },
                "time": {
                    "real": {
                        "departure": 1710253516
                    }
                }
            },
            {
                "identification": {
                    "id": "34548f21",
                    "number": {
                        "default": "CZ3914"
                    }
                },
                "airport": {
                    "origin": {
                        "name": "Harbin Taiping International Airport",
                        "code": {
                            "iata": "HRB",
                            "icao": "ZYHB"
                        },
                        "position": {
                            "latitude": 45.623402,
                            "longitude": 126.250298,
                            "altitude": 457,
                            "country": {
                                "id": null,
                                "name": "China",
                                "code": "CHN"
                            },
                            "region": {
                                "city": "Harbin"
                            }
                        },
                        "timezone": {
                            "name": "Asia/Harbin",
                            "offset": 28800,
                            "offsetHours": "8:00",
                            "abbr": "CST",
                            "abbrName": "China Standard Time",
                            "isDst": false
                        },
                        "visible": true,
                        "website": null
                    },
                    "destination": {
                        "name": "Guangzhou Baiyun International Airport",
                        "code": {
                            "iata": "CAN",
                            "icao": "ZGGG"
                        },
                        "position": {
                            "latitude": 23.392429,
                            "longitude": 113.298698,
                            "altitude": 50,
                            "country": {
                                "id": 46,
                                "name": "China",
                                "code": "CN",
                                "codeLong": "CHN"
                            },
                            "region": {
                                "city": "Guangzhou"
                            }
                        },
                        "timezone": {
                            "name": "Asia/Shanghai",
                            "offset": 28800,
                            "offsetHours": "8:00",
                            "abbr": "CST",
                            "abbrName": "China Standard Time",
                            "isDst": false
                        },
                        "visible": true,
                        "website": "http://www.gbiac.net/en/byhome"
                    }
                },
                "time": {
                    "real": {
                        "departure": 1710231279
                    }
                }
            },
            {
                "identification": {
                    "id": "34540e61",
                    "number": {
                        "default": "CZ3913"
                    }
                },
                "airport": {
                    "origin": {
                        "name": "Guangzhou Baiyun International Airport",
                        "code": {
                            "iata": "CAN",
                            "icao": "ZGGG"
                        },
                        "position": {
                            "latitude": 23.392429,
                            "longitude": 113.298698,
                            "altitude": 50,
                            "country": {
                                "id": 46,
                                "name": "China",
                                "code": "CN",
                                "codeLong": "CHN"
                            },
                            "region": {
                                "city": "Guangzhou"
                            }
                        },
                        "timezone": {
                            "name": "Asia/Shanghai",
                            "offset": 28800,
                            "offsetHours": "8:00",
                            "abbr": "CST",
                            "abbrName": "China Standard Time",
                            "isDst": false
                        },
                        "visible": true,
                        "website": "http://www.gbiac.net/en/byhome"
                    },
                    "destination": {
                        "name": "Harbin Taiping International Airport",
                        "code": {
                            "iata": "HRB",
                            "icao": "ZYHB"
                        },
                        "position": {
                            "latitude": 45.623402,
                            "longitude": 126.250298,
                            "altitude": 457,
                            "country": {
                                "id": null,
                                "name": "China",
                                "code": "CHN"
                            },
                            "region": {
                                "city": "Harbin"
                            }
                        },
                        "timezone": {
                            "name": "Asia/Harbin",
                            "offset": 28800,
                            "offsetHours": "8:00",
                            "abbr": "CST",
                            "abbrName": "China Standard Time",
                            "isDst": false
                        },
                        "visible": true,
                        "website": null
                    }
                },
                "time": {
                    "real": {
                        "departure": 1710212142
                    }
                }
            }
        ]
    },
    "ems": null,
    "availability": [
        "AGE",
        "MSN"
    ],
    "time": {
        "scheduled": {
            "departure": 1710298200,
            "arrival": 1710310500
        },
        "real": {
            "departure": 1710299812,
            "arrival": null
        },
        "estimated": {
            "departure": null,
            "arrival": 1710309120
        },
        "other": {
            "eta": 1710309120,
            "updated": 1710304699
        },
        "historical": {
            "flighttime": "10074",
            "delay": "-1909"
        }
    },
    "trail": [
        {
            "lat": 31.092773,
            "lng": 121.234833,
            "alt": 33100,
            "spd": 532,
            "ts": 1710304876,
            "hd": 77
        },
        {
            "lat": 31.066086,
            "lng": 121.119583,
            "alt": 33075,
            "spd": 529,
            "ts": 1710304837,
            "hd": 74
        },
        {
            "lat": 31.021454,
            "lng": 120.937393,
            "alt": 33050,
            "spd": 526,
            "ts": 1710304767,
            "hd": 74
        },
        {
            "lat": 30.99122,
            "lng": 120.814781,
            "alt": 33050,
            "spd": 526,
            "ts": 1710304722,
            "hd": 73
        },
        {
            "lat": 30.981995,
            "lng": 120.77771,
            "alt": 33050,
            "spd": 526,
            "ts": 1710304708,
            "hd": 74
        },
        {
            "lat": 30.962173,
            "lng": 120.697205,
            "alt": 33050,
            "spd": 526,
            "ts": 1710304678,
            "hd": 74
        },
        {
            "lat": 30.897978,
            "lng": 120.496178,
            "alt": 33125,
            "spd": 519,
            "ts": 1710304601,
            "hd": 58
        },
        {
            "lat": 30.893461,
            "lng": 120.48761,
            "alt": 33125,
            "spd": 518,
            "ts": 1710304597,
            "hd": 55
        },
        {
            "lat": 30.847046,
            "lng": 120.417908,
            "alt": 33150,
            "spd": 510,
            "ts": 1710304566,
            "hd": 46
        },
        {
            "lat": 30.789597,
            "lng": 120.358833,
            "alt": 33125,
            "spd": 500,
            "ts": 1710304533,
            "hd": 35
        },
        {
            "lat": 30.727083,
            "lng": 120.313583,
            "alt": 33125,
            "spd": 496,
            "ts": 1710304501,
            "hd": 30
        },
        {
            "lat": 30.66449,
            "lng": 120.270729,
            "alt": 33125,
            "spd": 496,
            "ts": 1710304469,
            "hd": 30
        },
        {
            "lat": 30.601393,
            "lng": 120.227402,
            "alt": 33125,
            "spd": 498,
            "ts": 1710304437,
            "hd": 30
        },
        {
            "lat": 30.538454,
            "lng": 120.184334,
            "alt": 33100,
            "spd": 498,
            "ts": 1710304406,
            "hd": 30
        },
        {
            "lat": 30.466484,
            "lng": 120.137093,
            "alt": 33100,
            "spd": 491,
            "ts": 1710304370,
            "hd": 26
        },
        {
            "lat": 30.399673,
            "lng": 120.099091,
            "alt": 33125,
            "spd": 490,
            "ts": 1710304337,
            "hd": 26
        },
        {
            "lat": 30.332088,
            "lng": 120.060516,
            "alt": 33100,
            "spd": 490,
            "ts": 1710304304,
            "hd": 26
        },
        {
            "lat": 30.261282,
            "lng": 120.020416,
            "alt": 33100,
            "spd": 490,
            "ts": 1710304270,
            "hd": 26
        },
        {
            "lat": 30.197832,
            "lng": 119.984329,
            "alt": 33100,
            "spd": 492,
            "ts": 1710304238,
            "hd": 26
        },
        {
            "lat": 30.085051,
            "lng": 119.920464,
            "alt": 33075,
            "spd": 491,
            "ts": 1710304183,
            "hd": 26
        },
        {
            "lat": 29.97261,
            "lng": 119.856827,
            "alt": 33075,
            "spd": 491,
            "ts": 1710304128,
            "hd": 26
        },
        {
            "lat": 29.84193,
            "lng": 119.779182,
            "alt": 33100,
            "spd": 500,
            "ts": 1710304063,
            "hd": 31
        },
        {
            "lat": 29.725929,
            "lng": 119.68457,
            "alt": 33100,
            "spd": 521,
            "ts": 1710304003,
            "hd": 40
        },
        {
            "lat": 29.62248,
            "lng": 119.564049,
            "alt": 33125,
            "spd": 538,
            "ts": 1710303943,
            "hd": 48
        },
        {
            "lat": 29.422178,
            "lng": 119.309044,
            "alt": 33100,
            "spd": 541,
            "ts": 1710303823,
            "hd": 47
        },
        {
            "lat": 29.32963,
            "lng": 119.191322,
            "alt": 33100,
            "spd": 542,
            "ts": 1710303768,
            "hd": 48
        },
        {
            "lat": 29.302631,
            "lng": 119.15696,
            "alt": 33075,
            "spd": 542,
            "ts": 1710303752,
            "hd": 47
        },
        {
            "lat": 29.166733,
            "lng": 118.985947,
            "alt": 33075,
            "spd": 543,
            "ts": 1710303671,
            "hd": 47
        },
        {
            "lat": 29.151058,
            "lng": 118.966316,
            "alt": 33075,
            "spd": 545,
            "ts": 1710303662,
            "hd": 47
        },
        {
            "lat": 29.01643,
            "lng": 118.797211,
            "alt": 33100,
            "spd": 546,
            "ts": 1710303583,
            "hd": 47
        },
        {
            "lat": 28.811649,
            "lng": 118.541672,
            "alt": 33125,
            "spd": 552,
            "ts": 1710303463,
            "hd": 47
        },
        {
            "lat": 28.708191,
            "lng": 118.413391,
            "alt": 33100,
            "spd": 552,
            "ts": 1710303403,
            "hd": 47
        },
        {
            "lat": 28.56665,
            "lng": 118.238243,
            "alt": 33100,
            "spd": 550,
            "ts": 1710303321,
            "hd": 47
        },
        {
            "lat": 28.543716,
            "lng": 118.20993,
            "alt": 33100,
            "spd": 549,
            "ts": 1710303308,
            "hd": 47
        },
        {
            "lat": 28.488327,
            "lng": 118.141533,
            "alt": 33100,
            "spd": 548,
            "ts": 1710303276,
            "hd": 47
        },
        {
            "lat": 28.381485,
            "lng": 118.01033,
            "alt": 33125,
            "spd": 542,
            "ts": 1710303213,
            "hd": 46
        },
        {
            "lat": 28.293779,
            "lng": 117.90686,
            "alt": 33100,
            "spd": 536,
            "ts": 1710303163,
            "hd": 44
        },
        {
            "lat": 28.257065,
            "lng": 117.867828,
            "alt": 33075,
            "spd": 528,
            "ts": 1710303144,
            "hd": 41
        },
        {
            "lat": 28.202835,
            "lng": 117.818298,
            "alt": 33075,
            "spd": 516,
            "ts": 1710303114,
            "hd": 37
        },
        {
            "lat": 28.138641,
            "lng": 117.763718,
            "alt": 33075,
            "spd": 514,
            "ts": 1710303080,
            "hd": 37
        },
        {
            "lat": 28.078169,
            "lng": 117.706062,
            "alt": 33125,
            "spd": 528,
            "ts": 1710303047,
            "hd": 44
        },
        {
            "lat": 28.025894,
            "lng": 117.645668,
            "alt": 33125,
            "spd": 532,
            "ts": 1710303017,
            "hd": 46
        },
        {
            "lat": 27.969376,
            "lng": 117.579399,
            "alt": 33100,
            "spd": 532,
            "ts": 1710302984,
            "hd": 46
        },
        {
            "lat": 27.91214,
            "lng": 117.512405,
            "alt": 33100,
            "spd": 530,
            "ts": 1710302950,
            "hd": 46
        },
        {
            "lat": 27.860304,
            "lng": 117.451767,
            "alt": 33100,
            "spd": 530,
            "ts": 1710302920,
            "hd": 46
        },
        {
            "lat": 27.803421,
            "lng": 117.385391,
            "alt": 33100,
            "spd": 528,
            "ts": 1710302886,
            "hd": 46
        },
        {
            "lat": 27.73645,
            "lng": 117.307503,
            "alt": 33100,
            "spd": 527,
            "ts": 1710302847,
            "hd": 45
        },
        {
            "lat": 27.634003,
            "lng": 117.188362,
            "alt": 33100,
            "spd": 526,
            "ts": 1710302787,
            "hd": 45
        },
        {
            "lat": 27.598206,
            "lng": 117.146904,
            "alt": 33075,
            "spd": 526,
            "ts": 1710302765,
            "hd": 45
        },
        {
            "lat": 27.540956,
            "lng": 117.080666,
            "alt": 33100,
            "spd": 525,
            "ts": 1710302732,
            "hd": 45
        },
        {
            "lat": 27.4904,
            "lng": 117.022354,
            "alt": 33100,
            "spd": 524,
            "ts": 1710302702,
            "hd": 45
        },
        {
            "lat": 27.434372,
            "lng": 116.956871,
            "alt": 33125,
            "spd": 524,
            "ts": 1710302669,
            "hd": 46
        },
        {
            "lat": 27.37779,
            "lng": 116.890678,
            "alt": 33100,
            "spd": 524,
            "ts": 1710302635,
            "hd": 46
        },
        {
            "lat": 27.322906,
            "lng": 116.826492,
            "alt": 33075,
            "spd": 524,
            "ts": 1710302602,
            "hd": 46
        },
        {
            "lat": 27.272003,
            "lng": 116.767097,
            "alt": 33075,
            "spd": 522,
            "ts": 1710302572,
            "hd": 46
        },
        {
            "lat": 27.216248,
            "lng": 116.702324,
            "alt": 33100,
            "spd": 521,
            "ts": 1710302539,
            "hd": 45
        },
        {
            "lat": 27.159693,
            "lng": 116.636879,
            "alt": 33100,
            "spd": 524,
            "ts": 1710302505,
            "hd": 47
        },
        {
            "lat": 27.109976,
            "lng": 116.576454,
            "alt": 33075,
            "spd": 525,
            "ts": 1710302475,
            "hd": 47
        },
        {
            "lat": 27.052826,
            "lng": 116.507317,
            "alt": 33075,
            "spd": 524,
            "ts": 1710302440,
            "hd": 47
        },
        {
            "lat": 27.003649,
            "lng": 116.447792,
            "alt": 33075,
            "spd": 523,
            "ts": 1710302411,
            "hd": 47
        },
        {
            "lat": 26.948997,
            "lng": 116.381767,
            "alt": 33075,
            "spd": 524,
            "ts": 1710302377,
            "hd": 47
        },
        {
            "lat": 26.893507,
            "lng": 116.314949,
            "alt": 33100,
            "spd": 522,
            "ts": 1710302344,
            "hd": 47
        },
        {
            "lat": 26.844681,
            "lng": 116.256187,
            "alt": 33100,
            "spd": 522,
            "ts": 1710302314,
            "hd": 47
        },
        {
            "lat": 26.789566,
            "lng": 116.189957,
            "alt": 33125,
            "spd": 524,
            "ts": 1710302281,
            "hd": 47
        },
        {
            "lat": 26.733088,
            "lng": 116.123642,
            "alt": 33150,
            "spd": 518,
            "ts": 1710302247,
            "hd": 44
        },
        {
            "lat": 26.674988,
            "lng": 116.066566,
            "alt": 33150,
            "spd": 507,
            "ts": 1710302214,
            "hd": 38
        },
        {
            "lat": 26.611261,
            "lng": 116.016312,
            "alt": 33125,
            "spd": 495,
            "ts": 1710302181,
            "hd": 31
        },
        {
            "lat": 26.551954,
            "lng": 115.978706,
            "alt": 33125,
            "spd": 485,
            "ts": 1710302151,
            "hd": 27
        },
        {
            "lat": 26.485058,
            "lng": 115.940254,
            "alt": 33125,
            "spd": 483,
            "ts": 1710302117,
            "hd": 27
        },
        {
            "lat": 26.424957,
            "lng": 115.905655,
            "alt": 33100,
            "spd": 482,
            "ts": 1710302087,
            "hd": 27
        },
        {
            "lat": 26.359274,
            "lng": 115.86805,
            "alt": 33100,
            "spd": 479,
            "ts": 1710302054,
            "hd": 27
        },
        {
            "lat": 26.293854,
            "lng": 115.82782,
            "alt": 33100,
            "spd": 490,
            "ts": 1710302020,
            "hd": 32
        },
        {
            "lat": 26.231255,
            "lng": 115.779945,
            "alt": 33150,
            "spd": 506,
            "ts": 1710301987,
            "hd": 37
        },
        {
            "lat": 26.171156,
            "lng": 115.723274,
            "alt": 33150,
            "spd": 517,
            "ts": 1710301954,
            "hd": 43
        },
        {
            "lat": 26.118784,
            "lng": 115.662956,
            "alt": 33150,
            "spd": 526,
            "ts": 1710301923,
            "hd": 48
        },
        {
            "lat": 26.115248,
            "lng": 115.658516,
            "alt": 33125,
            "spd": 526,
            "ts": 1710301921,
            "hd": 48
        },
        {
            "lat": 26.108543,
            "lng": 115.650223,
            "alt": 33150,
            "spd": 526,
            "ts": 1710301917,
            "hd": 48
        },
        {
            "lat": 26.104168,
            "lng": 115.644783,
            "alt": 33125,
            "spd": 525,
            "ts": 1710301914,
            "hd": 47
        },
        {
            "lat": 26.099932,
            "lng": 115.639557,
            "alt": 33125,
            "spd": 524,
            "ts": 1710301911,
            "hd": 46
        },
        {
            "lat": 26.093033,
            "lng": 115.631363,
            "alt": 33125,
            "spd": 520,
            "ts": 1710301907,
            "hd": 44
        },
        {
            "lat": 26.089325,
            "lng": 115.627167,
            "alt": 33125,
            "spd": 519,
            "ts": 1710301905,
            "hd": 43
        },
        {
            "lat": 26.082413,
            "lng": 115.619705,
            "alt": 33100,
            "spd": 516,
            "ts": 1710301902,
            "hd": 40
        },
        {
            "lat": 26.079071,
            "lng": 115.61628,
            "alt": 33100,
            "spd": 511,
            "ts": 1710301899,
            "hd": 40
        },
        {
            "lat": 26.071884,
            "lng": 115.609337,
            "alt": 33100,
            "spd": 509,
            "ts": 1710301895,
            "hd": 39
        },
        {
            "lat": 26.06632,
            "lng": 115.604218,
            "alt": 33100,
            "spd": 507,
            "ts": 1710301892,
            "hd": 38
        },
        {
            "lat": 26.011734,
            "lng": 115.565758,
            "alt": 33100,
            "spd": 486,
            "ts": 1710301864,
            "hd": 27
        },
        {
            "lat": 25.954781,
            "lng": 115.533493,
            "alt": 33100,
            "spd": 484,
            "ts": 1710301835,
            "hd": 27
        },
        {
            "lat": 25.88891,
            "lng": 115.496155,
            "alt": 33075,
            "spd": 483,
            "ts": 1710301802,
            "hd": 27
        },
        {
            "lat": 25.82951,
            "lng": 115.462555,
            "alt": 33050,
            "spd": 483,
            "ts": 1710301773,
            "hd": 27
        },
        {
            "lat": 25.762848,
            "lng": 115.424858,
            "alt": 33075,
            "spd": 483,
            "ts": 1710301739,
            "hd": 27
        },
        {
            "lat": 25.702606,
            "lng": 115.390831,
            "alt": 33075,
            "spd": 483,
            "ts": 1710301709,
            "hd": 27
        },
        {
            "lat": 25.635681,
            "lng": 115.353088,
            "alt": 33075,
            "spd": 484,
            "ts": 1710301676,
            "hd": 27
        },
        {
            "lat": 25.569328,
            "lng": 115.315712,
            "alt": 33100,
            "spd": 485,
            "ts": 1710301642,
            "hd": 27
        },
        {
            "lat": 25.496986,
            "lng": 115.274979,
            "alt": 33100,
            "spd": 488,
            "ts": 1710301606,
            "hd": 27
        },
        {
            "lat": 25.428555,
            "lng": 115.236526,
            "alt": 33100,
            "spd": 488,
            "ts": 1710301572,
            "hd": 27
        },
        {
            "lat": 25.367065,
            "lng": 115.202026,
            "alt": 33100,
            "spd": 485,
            "ts": 1710301542,
            "hd": 26
        },
        {
            "lat": 25.299232,
            "lng": 115.164078,
            "alt": 33100,
            "spd": 480,
            "ts": 1710301508,
            "hd": 27
        },
        {
            "lat": 25.124241,
            "lng": 115.066238,
            "alt": 32575,
            "spd": 472,
            "ts": 1710301419,
            "hd": 26
        },
        {
            "lat": 25.107065,
            "lng": 115.056656,
            "alt": 32500,
            "spd": 473,
            "ts": 1710301412,
            "hd": 26
        },
        {
            "lat": 24.928816,
            "lng": 114.957314,
            "alt": 31025,
            "spd": 477,
            "ts": 1710301321,
            "hd": 26
        },
        {
            "lat": 24.827612,
            "lng": 114.901085,
            "alt": 30400,
            "spd": 472,
            "ts": 1710301268,
            "hd": 26
        },
        {
            "lat": 24.764648,
            "lng": 114.866127,
            "alt": 29950,
            "spd": 473,
            "ts": 1710301236,
            "hd": 26
        },
        {
            "lat": 24.614216,
            "lng": 114.782982,
            "alt": 28975,
            "spd": 468,
            "ts": 1710301159,
            "hd": 26
        },
        {
            "lat": 24.567764,
            "lng": 114.757332,
            "alt": 28625,
            "spd": 468,
            "ts": 1710301135,
            "hd": 26
        },
        {
            "lat": 24.504959,
            "lng": 114.723,
            "alt": 28100,
            "spd": 465,
            "ts": 1710301103,
            "hd": 24
        },
        {
            "lat": 24.442291,
            "lng": 114.69381,
            "alt": 27725,
            "spd": 459,
            "ts": 1710301071,
            "hd": 22
        },
        {
            "lat": 24.378113,
            "lng": 114.664459,
            "alt": 27325,
            "spd": 456,
            "ts": 1710301038,
            "hd": 22
        },
        {
            "lat": 24.319885,
            "lng": 114.637856,
            "alt": 26950,
            "spd": 454,
            "ts": 1710301008,
            "hd": 22
        },
        {
            "lat": 24.254013,
            "lng": 114.607849,
            "alt": 26425,
            "spd": 454,
            "ts": 1710300974,
            "hd": 22
        },
        {
            "lat": 24.193338,
            "lng": 114.5802,
            "alt": 25650,
            "spd": 458,
            "ts": 1710300943,
            "hd": 22
        },
        {
            "lat": 24.128119,
            "lng": 114.550453,
            "alt": 24850,
            "spd": 461,
            "ts": 1710300910,
            "hd": 22
        },
        {
            "lat": 24.06752,
            "lng": 114.522858,
            "alt": 23975,
            "spd": 466,
            "ts": 1710300879,
            "hd": 22
        },
        {
            "lat": 24.001217,
            "lng": 114.492722,
            "alt": 23425,
            "spd": 459,
            "ts": 1710300846,
            "hd": 22
        },
        {
            "lat": 23.943026,
            "lng": 114.46624,
            "alt": 22950,
            "spd": 453,
            "ts": 1710300816,
            "hd": 22
        },
        {
            "lat": 23.87883,
            "lng": 114.436897,
            "alt": 22650,
            "spd": 435,
            "ts": 1710300782,
            "hd": 22
        },
        {
            "lat": 23.818266,
            "lng": 114.409447,
            "alt": 22450,
            "spd": 413,
            "ts": 1710300749,
            "hd": 22
        },
        {
            "lat": 23.75975,
            "lng": 114.382858,
            "alt": 21750,
            "spd": 402,
            "ts": 1710300716,
            "hd": 22
        },
        {
            "lat": 23.700714,
            "lng": 114.355721,
            "alt": 20075,
            "spd": 415,
            "ts": 1710300682,
            "hd": 22
        },
        {
            "lat": 23.695461,
            "lng": 114.353371,
            "alt": 19875,
            "spd": 420,
            "ts": 1710300679,
            "hd": 22
        },
        {
            "lat": 23.691605,
            "lng": 114.351601,
            "alt": 19750,
            "spd": 422,
            "ts": 1710300676,
            "hd": 24
        },
        {
            "lat": 23.685406,
            "lng": 114.348816,
            "alt": 19575,
            "spd": 422,
            "ts": 1710300673,
            "hd": 24
        },
        {
            "lat": 23.679382,
            "lng": 114.346008,
            "alt": 19425,
            "spd": 426,
            "ts": 1710300670,
            "hd": 27
        },
        {
            "lat": 23.673019,
            "lng": 114.342598,
            "alt": 19325,
            "spd": 425,
            "ts": 1710300666,
            "hd": 29
        },
        {
            "lat": 23.669357,
            "lng": 114.340462,
            "alt": 19275,
            "spd": 425,
            "ts": 1710300664,
            "hd": 30
        },
        {
            "lat": 23.662903,
            "lng": 114.336342,
            "alt": 19175,
            "spd": 425,
            "ts": 1710300660,
            "hd": 33
        },
        {
            "lat": 23.608292,
            "lng": 114.286858,
            "alt": 18700,
            "spd": 429,
            "ts": 1710300624,
            "hd": 42
        },
        {
            "lat": 23.564026,
            "lng": 114.243011,
            "alt": 18700,
            "spd": 426,
            "ts": 1710300594,
            "hd": 42
        },
        {
            "lat": 23.51833,
            "lng": 114.197792,
            "alt": 18225,
            "spd": 427,
            "ts": 1710300563,
            "hd": 42
        },
        {
            "lat": 23.468124,
            "lng": 114.148048,
            "alt": 17025,
            "spd": 419,
            "ts": 1710300528,
            "hd": 42
        },
        {
            "lat": 23.426901,
            "lng": 114.107002,
            "alt": 16075,
            "spd": 411,
            "ts": 1710300499,
            "hd": 42
        },
        {
            "lat": 23.421873,
            "lng": 114.101967,
            "alt": 15975,
            "spd": 410,
            "ts": 1710300496,
            "hd": 42
        },
        {
            "lat": 23.417265,
            "lng": 114.097343,
            "alt": 15850,
            "spd": 408,
            "ts": 1710300492,
            "hd": 42
        },
        {
            "lat": 23.413834,
            "lng": 114.093964,
            "alt": 15775,
            "spd": 408,
            "ts": 1710300490,
            "hd": 42
        },
        {
            "lat": 23.409119,
            "lng": 114.089226,
            "alt": 15650,
            "spd": 406,
            "ts": 1710300487,
            "hd": 42
        },
        {
            "lat": 23.404882,
            "lng": 114.084984,
            "alt": 15525,
            "spd": 406,
            "ts": 1710300484,
            "hd": 43
        },
        {
            "lat": 23.401438,
            "lng": 114.08152,
            "alt": 15400,
            "spd": 406,
            "ts": 1710300481,
            "hd": 43
        },
        {
            "lat": 23.396875,
            "lng": 114.076897,
            "alt": 15250,
            "spd": 408,
            "ts": 1710300478,
            "hd": 43
        },
        {
            "lat": 23.392548,
            "lng": 114.072495,
            "alt": 15075,
            "spd": 409,
            "ts": 1710300475,
            "hd": 45
        },
        {
            "lat": 23.387844,
            "lng": 114.06723,
            "alt": 14925,
            "spd": 412,
            "ts": 1710300471,
            "hd": 52
        },
        {
            "lat": 23.384819,
            "lng": 114.063515,
            "alt": 14800,
            "spd": 412,
            "ts": 1710300469,
            "hd": 52
        },
        {
            "lat": 23.368851,
            "lng": 114.036003,
            "alt": 14150,
            "spd": 414,
            "ts": 1710300453,
            "hd": 64
        },
        {
            "lat": 23.34137,
            "lng": 113.973763,
            "alt": 12900,
            "spd": 411,
            "ts": 1710300420,
            "hd": 64
        },
        {
            "lat": 23.316013,
            "lng": 113.910927,
            "alt": 12775,
            "spd": 405,
            "ts": 1710300386,
            "hd": 70
        },
        {
            "lat": 23.300583,
            "lng": 113.849319,
            "alt": 12100,
            "spd": 378,
            "ts": 1710300355,
            "hd": 77
        },
        {
            "lat": 23.294083,
            "lng": 113.817757,
            "alt": 11575,
            "spd": 360,
            "ts": 1710300337,
            "hd": 77
        },
        {
            "lat": 23.288363,
            "lng": 113.790077,
            "alt": 11050,
            "spd": 348,
            "ts": 1710300321,
            "hd": 77
        },
        {
            "lat": 23.282547,
            "lng": 113.762932,
            "alt": 10500,
            "spd": 335,
            "ts": 1710300305,
            "hd": 76
        },
        {
            "lat": 23.277794,
            "lng": 113.741051,
            "alt": 10050,
            "spd": 326,
            "ts": 1710300291,
            "hd": 76
        },
        {
            "lat": 23.273026,
            "lng": 113.71978,
            "alt": 9650,
            "spd": 320,
            "ts": 1710300279,
            "hd": 76
        },
        {
            "lat": 23.267508,
            "lng": 113.692223,
            "alt": 8975,
            "spd": 313,
            "ts": 1710300260,
            "hd": 82
        },
        {
            "lat": 23.266855,
            "lng": 113.687538,
            "alt": 8875,
            "spd": 312,
            "ts": 1710300257,
            "hd": 85
        },
        {
            "lat": 23.26712,
            "lng": 113.661751,
            "alt": 8100,
            "spd": 307,
            "ts": 1710300241,
            "hd": 94
        },
        {
            "lat": 23.271652,
            "lng": 113.547897,
            "alt": 6725,
            "spd": 278,
            "ts": 1710300166,
            "hd": 92
        },
        {
            "lat": 23.271469,
            "lng": 113.554443,
            "alt": 6725,
            "spd": 278,
            "ts": 1710300166,
            "hd": 92
        },
        {
            "lat": 23.271883,
            "lng": 113.54055,
            "alt": 6725,
            "spd": 278,
            "ts": 1710300156,
            "hd": 92
        },
        {
            "lat": 23.276863,
            "lng": 113.387047,
            "alt": 6675,
            "spd": 277,
            "ts": 1710300063,
            "hd": 92
        },
        {
            "lat": 23.275818,
            "lng": 113.409966,
            "alt": 6675,
            "spd": 277,
            "ts": 1710300063,
            "hd": 92
        },
        {
            "lat": 23.275839,
            "lng": 113.408508,
            "alt": 6675,
            "spd": 277,
            "ts": 1710300061,
            "hd": 92
        },
        {
            "lat": 23.275955,
            "lng": 113.404976,
            "alt": 6675,
            "spd": 277,
            "ts": 1710300059,
            "hd": 92
        },
        {
            "lat": 23.276165,
            "lng": 113.400017,
            "alt": 6675,
            "spd": 276,
            "ts": 1710300055,
            "hd": 92
        },
        {
            "lat": 23.276398,
            "lng": 113.393913,
            "alt": 6650,
            "spd": 274,
            "ts": 1710300051,
            "hd": 93
        },
        {
            "lat": 23.278307,
            "lng": 113.375801,
            "alt": 6475,
            "spd": 250,
            "ts": 1710300037,
            "hd": 102
        },
        {
            "lat": 23.282593,
            "lng": 113.357384,
            "alt": 6125,
            "spd": 226,
            "ts": 1710300022,
            "hd": 103
        },
        {
            "lat": 23.285988,
            "lng": 113.341522,
            "alt": 5725,
            "spd": 208,
            "ts": 1710300007,
            "hd": 102
        },
        {
            "lat": 23.289154,
            "lng": 113.326668,
            "alt": 5200,
            "spd": 192,
            "ts": 1710299992,
            "hd": 113
        },
        {
            "lat": 23.294415,
            "lng": 113.316551,
            "alt": 4725,
            "spd": 182,
            "ts": 1710299980,
            "hd": 137
        },
        {
            "lat": 23.33445,
            "lng": 113.305656,
            "alt": 2900,
            "spd": 151,
            "ts": 1710299926,
            "hd": 178
        }
    ],
    "firstTimestamp": 1710299926,
    "s": "2QN-1YKwGuDNyYdHj1hOHLL1WYv8RjxbE_luQ6-haBl1fJf7a2GWN3xESbu7sej4"
}